[
    {
    "t": "和平区",
    "s": [{
        "t": "南市街道"
    }, {
        "t": "南营门街道"
    }, {
        "t": "新兴街道"
    }, {
        "t": "体育馆街道"
    }, {
        "t": "小白楼街道"
    }, {
        "t": "劝业场街道"
    }]
    },
    {
    "t": "河东区",
    "s": [{
        "t": "天津铁厂街道"
    }, {
        "t": "鲁山道街道"
    }, {
        "t": "东新街道"
    }, {
        "t": "上杭路街道"
    }, {
        "t": "常州道街道"
    }, {
        "t": "向阳楼街道"
    }, {
        "t": "唐家口街道"
    }, {
        "t": "春华街道"
    }, {
        "t": "二号桥街道"
    }, {
        "t": "富民路街道"
    }, {
        "t": "中山门街道"
    }, {
        "t": "大直沽街道"
    }, {
        "t": "大王庄街道"
    }]
}, {
    "t": "河西区",
    "s": [{
        "t": "梅江街道"
    }, {
        "t": "东海街道"
    }, {
        "t": "柳林街道"
    }, {
        "t": "陈塘庄街道"
    }, {
        "t": "尖山街道"
    }, {
        "t": "天塔街道"
    }, {
        "t": "友谊路街道"
    }, {
        "t": "越秀路街道"
    }, {
        "t": "马场街道"
    }, {
        "t": "挂甲寺街道"
    }, {
        "t": "桃园街道"
    }, {
        "t": "下瓦房街道"
    }, {
        "t": "大营门街道"
    }]
}, {
    "t": "南开区",
    "s": [{
        "t": "华苑街道"
    }, {
        "t": "体育中心街道"
    }, {
        "t": "八里台街道"
    }, {
        "t": "王顶堤街道"
    }, {
        "t": "嘉陵道街道"
    }, {
        "t": "向阳路街道"
    }, {
        "t": "学府街道"
    }, {
        "t": "万兴街道"
    }, {
        "t": "广开街道"
    }, {
        "t": "兴南街道"
    }, {
        "t": "鼓楼街道"
    }, {
        "t": "长虹街道"
    }]
}, {
    "t": "河北区",
    "s": [{
        "t": "月牙河街道"
    }, {
        "t": "江都路街道"
    }, {
        "t": "王串场街道"
    }, {
        "t": "宁园街道"
    }, {
        "t": "建昌道街道"
    }, {
        "t": "铁东路街道"
    }, {
        "t": "新开河街道"
    }, {
        "t": "鸿顺里街道"
    }, {
        "t": "望海楼街道"
    }, {
        "t": "光复道街道"
    }]
}, {
    "t": "红桥区",
    "s": [{
        "t": "大胡同街道"
    }, {
        "t": "铃铛阁街道"
    }, {
        "t": "芥园道街道"
    }, {
        "t": "邵公庄街道"
    }, {
        "t": "三条石街道"
    }, {
        "t": "西沽街道"
    }, {
        "t": "丁字沽街道"
    }, {
        "t": "咸阳北路街道"
    }, {
        "t": "双环村街道"
    }, {
        "t": "西于庄街道"
    }]
}, {
    "t": "塘沽区",
    "s": [{
        "t": "新城镇"
    }, {
        "t": "胡家园街道"
    }, {
        "t": "渤海石油街道"
    }, {
        "t": "北塘街道"
    }, {
        "t": "大沽街道"
    }, {
        "t": "新河街道"
    }, {
        "t": "杭州道街道"
    }, {
        "t": "向阳街道"
    }, {
        "t": "新港街道"
    }, {
        "t": "三槐路街道"
    }, {
        "t": "解放路街道"
    }, {
        "t": "新村街道"
    }]
}, {
    "t": "大港区",
    "s": [{
        "t": "中塘镇"
    }, {
        "t": "小王庄镇"
    }, {
        "t": "太平镇"
    }, {
        "t": "港西街道"
    }, {
        "t": "海滨街道"
    }, {
        "t": "古林街道"
    }, {
        "t": "胜利街道"
    }, {
        "t": "迎宾街道"
    }]
}, {
    "t": "东丽区 ",
    "s": [{
        "t": "么六桥乡"
    }, {
        "t": "华明镇"
    }, {
        "t": "大毕庄镇"
    }, {
        "t": "军粮城镇"
    }, {
        "t": "新立街道"
    }, {
        "t": "无瑕街道"
    }, {
        "t": "万新街道"
    }, {
        "t": "丰年村街道"
    }, {
        "t": "张贵庄街道"
    }]
}, {
    "t": "西青区",
    "s": [{
        "t": "王稳庄镇"
    }, {
        "t": "大寺镇"
    }, {
        "t": "南河镇"
    }, {
        "t": "张家窝镇"
    }, {
        "t": "辛口镇"
    }, {
        "t": "杨柳青镇"
    }, {
        "t": "中北镇"
    }, {
        "t": "李七庄街道"
    }, {
        "t": "西营门街道"
    }]
}, {
    "t": "津南区",
    "s": [{
        "t": "长青办事处"
    }, {
        "t": "北闸口镇"
    }, {
        "t": "八里台镇"
    }, {
        "t": "双桥河镇"
    }, {
        "t": "辛庄镇"
    }, {
        "t": "双港镇"
    }, {
        "t": "小站镇"
    }, {
        "t": "葛沽镇"
    }, {
        "t": "咸水沽镇"
    }]
}, {
    "t": "北辰区",
    "s": [{
        "t": "西堤头镇"
    }, {
        "t": "大张庄镇"
    }, {
        "t": "小淀镇"
    }, {
        "t": "宜兴埠镇"
    }, {
        "t": "青光镇"
    }, {
        "t": "双口镇"
    }, {
        "t": "双街镇"
    }, {
        "t": "北仓镇"
    }, {
        "t": "天穆镇"
    }, {
        "t": "普东街道"
    }, {
        "t": "集贤里街道"
    }, {
        "t": "果园新村街道"
    }]
}, {
    "t": "蓟县",
    "s": [{
        "t": "东赵各庄乡"
    }, {
        "t": "礼明庄乡"
    }, {
        "t": "许家台乡"
    }, {
        "t": "东二营乡"
    }, {
        "t": "孙各庄满族乡"
    }, {
        "t": "穿芳峪乡"
    }, {
        "t": "西龙虎峪镇"
    }, {
        "t": "出头岭镇"
    }, {
        "t": "杨津庄镇"
    }, {
        "t": "下窝头镇"
    }, {
        "t": "东施古镇"
    }, {
        "t": "桑梓镇"
    }, {
        "t": "侯家营镇"
    }, {
        "t": "五百户镇"
    }, {
        "t": "白涧镇"
    }, {
        "t": "罗庄子镇"
    }, {
        "t": "下仓镇"
    }, {
        "t": "上仓镇"
    }, {
        "t": "尤古庄镇"
    }, {
        "t": "别山镇"
    }, {
        "t": "邦均镇"
    }, {
        "t": "下营镇"
    }, {
        "t": "马伸桥镇"
    }, {
        "t": "官庄镇"
    }, {
        "t": "洇溜镇"
    }, {
        "t": "城关镇"
    }, {
        "t": "文昌街道"
    }]
}, {
    "t": "宝坻区",
    "s": [{
        "t": "黄庄乡"
    }, {
        "t": "尔王庄乡"
    }, {
        "t": "牛家牌乡"
    }, {
        "t": "周良庄镇"
    }, {
        "t": "郝各庄镇"
    }, {
        "t": "史各庄镇"
    }, {
        "t": "牛道口镇"
    }, {
        "t": "口东镇"
    }, {
        "t": "高家庄镇"
    }, {
        "t": "大唐庄镇"
    }, {
        "t": "新开口镇"
    }, {
        "t": "霍各庄镇"
    }, {
        "t": "马家店镇"
    }, {
        "t": "新安镇"
    }, {
        "t": "大钟庄镇"
    }, {
        "t": "八门城镇"
    }, {
        "t": "林亭口镇"
    }, {
        "t": "方家庄镇"
    }, {
        "t": "王卜庄镇"
    }, {
        "t": "大白庄镇"
    }, {
        "t": "大口屯镇"
    }, {
        "t": "城关镇"
    }]
}, {
    "t": "武清区 ",
    "s": [{
        "t": "白古屯乡"
    }, {
        "t": "高村乡"
    }, {
        "t": "大黄堡乡"
    }, {
        "t": "曹子里乡"
    }, {
        "t": "豆张庄乡"
    }, {
        "t": "陈咀镇"
    }, {
        "t": "大王古庄镇"
    }, {
        "t": "上马台镇"
    }, {
        "t": "河北屯镇"
    }, {
        "t": "汊沽港镇"
    }, {
        "t": "王庆坨镇"
    }, {
        "t": "石各庄镇"
    }, {
        "t": "黄花店镇"
    }, {
        "t": "东马圈镇"
    }, {
        "t": "城关镇"
    }, {
        "t": "河西务镇"
    }, {
        "t": "泗村店镇"
    }, {
        "t": "大孟庄镇"
    }, {
        "t": "南蔡村镇"
    }, {
        "t": "下伍旗镇"
    }, {
        "t": "大良镇"
    }, {
        "t": "崔黄口镇"
    }, {
        "t": "大碱厂镇"
    }, {
        "t": "梅厂镇"
    }, {
        "t": "运河西街道"
    }, {
        "t": "徐官屯街道"
    }, {
        "t": "黄庄街道"
    }, {
        "t": "东蒲洼街道"
    }, {
        "t": "下朱庄街道"
    }, {
        "t": "杨村街道"
    }]
}, {
    "t": "宁河县",
    "s": [{
        "t": "廉庄子乡"
    }, {
        "t": "俵口乡"
    }, {
        "t": "北淮淀乡"
    }, {
        "t": "东棘坨镇"
    }, {
        "t": "大北涧沽镇"
    }, {
        "t": "七里海镇"
    }, {
        "t": "造甲城镇"
    }, {
        "t": "潘庄镇"
    }, {
        "t": "板桥镇"
    }, {
        "t": "岳龙镇"
    }, {
        "t": "丰台镇"
    }, {
        "t": "苗庄镇"
    }, {
        "t": "宁河镇"
    }, {
        "t": "芦台镇"
    }]
}, {
    "t": "静海县",
    "s": [{
        "t": "杨成庄乡"
    }, {
        "t": "良王庄乡"
    }, {
        "t": "西翟庄镇"
    }, {
        "t": "沿庄镇"
    }, {
        "t": "大丰堆镇"
    }, {
        "t": "双塘镇"
    }, {
        "t": "团泊镇"
    }, {
        "t": "梁头镇"
    }, {
        "t": "蔡公庄镇"
    }, {
        "t": "大邱庄镇"
    }, {
        "t": "中旺镇"
    }, {
        "t": "陈官屯镇"
    }, {
        "t": "子牙镇"
    }, {
        "t": "台头镇"
    }, {
        "t": "王口镇"
    }, {
        "t": "独流镇"
    }, {
        "t": "唐官屯镇"
    }, {
        "t": "静海镇"
    }]
}, {
    "t": "汉沽区",
    "s": [{
        "t": "营城镇"
    }, {
        "t": "茶淀镇"
    }, {
        "t": "杨家泊镇"
    }, {
        "t": "大田镇"
    }, {
        "t": "盐场街道"
    }, {
        "t": "天化街道"
    }, {
        "t": "河西街道"
    }, {
        "t": "寨上街道"
    }, {
        "t": "汉沽街道"
    }]
}, {
    "t": "其它地区",
    "s": [{
        "t": "其它"
    }]
}]